ctfcli/__init__.py
ctfcli/__main__.py
ctfcli/cli/__init__.py
ctfcli/cli/challenges.py
ctfcli/cli/config.py
ctfcli/cli/pages.py
ctfcli/cli/plugins.py
ctfcli/cli/templates.py
ctfcli/spec/challenge-example.yml
ctfcli/templates/binary/default/cookiecutter.json
ctfcli/templates/binary/default/{{cookiecutter.name}}/.dockerignore
ctfcli/templates/binary/default/{{cookiecutter.name}}/Makefile
ctfcli/templates/binary/default/{{cookiecutter.name}}/README.md
ctfcli/templates/binary/default/{{cookiecutter.name}}/challenge.yml
ctfcli/templates/binary/default/{{cookiecutter.name}}/src/{{cookiecutter.name}}.c
ctfcli/templates/binary/default/{{cookiecutter.name}}/writeup/WRITEUP.md
ctfcli/templates/blank/default/cookiecutter.json
ctfcli/templates/blank/default/{{cookiecutter.name}}/README.md
ctfcli/templates/blank/default/{{cookiecutter.name}}/challenge.yml
ctfcli/templates/blank/default/{{cookiecutter.name}}/src/placeholder
ctfcli/templates/blank/default/{{cookiecutter.name}}/writeup/WRITEUP.md
ctfcli/templates/crypto/default/cookiecutter.json
ctfcli/templates/crypto/default/{{cookiecutter.name}}/.gitignore
ctfcli/templates/crypto/default/{{cookiecutter.name}}/Makefile
ctfcli/templates/crypto/default/{{cookiecutter.name}}/README.md
ctfcli/templates/crypto/default/{{cookiecutter.name}}/challenge.yml
ctfcli/templates/crypto/default/{{cookiecutter.name}}/src/encrypt.py
ctfcli/templates/crypto/default/{{cookiecutter.name}}/src/flag.txt
ctfcli/templates/crypto/default/{{cookiecutter.name}}/writeup/WRITEUP.md
ctfcli/templates/programming/default/cookiecutter.json
ctfcli/templates/programming/default/{{cookiecutter.name}}/.dockerignore
ctfcli/templates/programming/default/{{cookiecutter.name}}/.gitignore
ctfcli/templates/programming/default/{{cookiecutter.name}}/Dockerfile
ctfcli/templates/programming/default/{{cookiecutter.name}}/README.md
ctfcli/templates/programming/default/{{cookiecutter.name}}/challenge.yml
reteps_ctfcli-0.0.14.dist-info/LICENSE
reteps_ctfcli-0.0.14.dist-info/METADATA
reteps_ctfcli-0.0.14.dist-info/WHEEL
reteps_ctfcli-0.0.14.dist-info/entry_points.txt
reteps_ctfcli-0.0.14.dist-info/top_level.txt
reteps_ctfcli-0.0.14.dist-info/RECORD
