Metadata-Version: 2.1
Name: reteps-ctfcli
Version: 0.0.14
Summary: Tool for creating and running Capture The Flag competitions
Author: Kevin Chung
Author-email: kchung@ctfd.io
License: Apache 2.0
Keywords: ctf
License-File: LICENSE
Requires-Dist: cookiecutter (==2.1.1)
Requires-Dist: click (==7.0)
Requires-Dist: fire (==0.2.1)
Requires-Dist: pyyaml (==6.0.1)
Requires-Dist: Pygments (==2.7.4)
Requires-Dist: requests (==2.28.1)
Requires-Dist: colorama (==0.4.6)
Requires-Dist: appdirs (==1.4.3)
Requires-Dist: python-frontmatter (==1.0.0)
